geogo/__init__.py
geogo/common.py
geogo/foliummap.py
geogo/geogo.py
geogo-1.0.0.dist-info/licenses/LICENSE
geogo-1.0.0.dist-info/METADATA
geogo-1.0.0.dist-info/WHEEL
geogo-1.0.0.dist-info/entry_points.txt
geogo-1.0.0.dist-info/top_level.txt
geogo-1.0.0.dist-info/RECORD
