Metadata-Version: 2.4
Name: geogo
Version: 1.0.0
Summary: A python package for geospatial analysis and mapping
Author-email: Jordyn Hammel <jlhammel134@gmail.com>
License: MIT License
Project-URL: Homepage, https://github.com/jlhammel/geogo
Keywords: geogo
Classifier: Intended Audience :: Developers
Classifier: License :: OSI Approved :: MIT License
Classifier: Natural Language :: English
Classifier: Programming Language :: Python :: 3.8
Classifier: Programming Language :: Python :: 3.9
Classifier: Programming Language :: Python :: 3.10
Classifier: Programming Language :: Python :: 3.11
Classifier: Programming Language :: Python :: 3.12
Requires-Python: >=3.8
License-File: LICENSE
Requires-Dist: fiona
Requires-Dist: folium
Requires-Dist: geopandas
Requires-Dist: ipyleaflet
Requires-Dist: leafmap
Requires-Dist: localtileserver
Requires-Dist: mapclassify
Requires-Dist: matplotlib
Requires-Dist: numpy
Requires-Dist: tropycal
Provides-Extra: all
Requires-Dist: geogo[extra]; extra == "all"
Provides-Extra: extra
Requires-Dist: pandas; extra == "extra"
Dynamic: license-file
